main.py
StickerViaBot/__init__.py
StickerViaBot/bot.py
StickerViaBot/default_pattern.py
StickerViaBot/plugin.py
StickerViaBot/utils.py
plugins/relay.py
StickerViaBot-0.2.2.dist-info/LICENSE
StickerViaBot-0.2.2.dist-info/METADATA
StickerViaBot-0.2.2.dist-info/WHEEL
StickerViaBot-0.2.2.dist-info/top_level.txt
StickerViaBot-0.2.2.dist-info/RECORD
