Metadata-Version: 2.1
Name: StickerViaBot
Version: 0.2.2
Summary: 一个用于生成 Sticker 的简易 Telegram Bot 框架
Home-page: https://github.com/67au/StickerViaBot
Maintainer: 67au
Maintainer-email: oyy6745@gmail.com
License: MIT License
Classifier: Programming Language :: Python :: 3.8
Classifier: Programming Language :: Python :: 3.9
Classifier: Programming Language :: Python :: 3.10
Classifier: License :: OSI Approved :: MIT License
Requires-Python: >=3.8
License-File: LICENSE
Requires-Dist: pyrogram ~=2.0.0
Requires-Dist: pluginlib ~=0.9.0
